flask_multipass_authentik.py
flask_multipass_authentik-0.0.3.dist-info/METADATA
flask_multipass_authentik-0.0.3.dist-info/WHEEL
flask_multipass_authentik-0.0.3.dist-info/entry_points.txt
flask_multipass_authentik-0.0.3.dist-info/licenses/LICENSE
flask_multipass_authentik-0.0.3.dist-info/RECORD
