Metadata-Version: 2.4
Name: Flask-Multipass-Authentik
Version: 0.0.3
Summary: Flask-Multipass provider for Authentik
License: MIT
License-File: LICENSE
Author: RobotHanzo
Author-email: admin@robothanzo.dev
Requires-Python: >=3.9,<4.0
Classifier: Development Status :: 3 - Alpha
Classifier: Environment :: Web Environment
Classifier: Framework :: Flask
Classifier: License :: OSI Approved :: MIT License
Classifier: Programming Language :: Python :: 3
Classifier: Programming Language :: Python :: 3.9
Classifier: Programming Language :: Python :: 3.10
Classifier: Programming Language :: Python :: 3.11
Classifier: Programming Language :: Python :: 3.12
Classifier: Programming Language :: Python :: 3.13
Classifier: Programming Language :: Python :: 3.14
Requires-Dist: authentik-client (>=2025.8.3,<2026.0.0)
Requires-Dist: flask-multipass[authlib] (>=0.4.3)
Project-URL: Repository, https://github.com/RobotHanzo/flask-multipass-authentik
